Workbook

Sheet Expense Directory
A1: Expense ID | B1: Date | C1: Expense Category | D1: Supplier / Worker / Note | E1: Amount Paid (Rs.) | F1: Remarks / Notes
A2: EXP-101 | B2: 2026-09-01 | C2: Silage | D2: Green Fodder Supplier | E2: 1200 | F2: Silage tractor load
A3: EXP-102 | B3: 2026-09-01 | C3: Grass Cutter Wage | D3: Murugan (Worker) | E3: 600 | F3: Daily grass cutting wage
A4: EXP-103 | B4: 2026-09-01 | C4: Feed / Punnaku | D4: Lakshmi Feed Store | E4: 450 | F4: 50kg Oil cake bag
A5: EXP-104 | B5: 2026-09-01 | C5: Other Expense | D5: Veterinary Doctor | E5: 100 | F5: Cow health checkup
A6: EXP-105 | B6: 2026-09-02 | C6: Grass Cutter Wage | D6: Murugan (Worker) | E6: 600 | F6: Daily wage
A7: EXP-106 | B7: 2026-09-02 | C7: Feed / Punnaku | D7: Lakshmi Feed Store | E7: 450 | F7: 50kg Oil cake bag
A8: EXP-107 | B8: 2026-09-03 | C8: Grass Cutter Wage | D8: Murugan (Worker) | E8: 600 | F8: Daily wage
A9: EXP-108 | B9: 2026-09-03 | C9: Feed / Punnaku | D9: Cow Store | E9: 500 | F9: Punnaku bag
A10: EXP-109 | B10: 2026-09-04 | C10: Silage | D10: Fodder Supplier | E10: 1200 | F10: New silage batch

Sheet Registered Customers
A1: Customer ID | B1: Customer Name | C1: Milk Category | D1: Customer Type | E1: Phone Number | F1: Delivery Route / Address | G1: Def 175ml | H1: Def 475ml | I1: Def 500ml | J1: Def 750ml | K1: Def 1L | L1: Status | M1: Total Litres Bought | N1: Total Revenue (Rs.)
A2: CUST-101 | B2: Dharshan | C2: Cow Milk | D2: Daily Customer | E2: 0764805061 | F2: Route 1 - Green Valley | G2: 0 | H2: 1 | I2: 0 | J2: 2 | K2: 1 | L2: Active | M2: =SUMIF('Daily Tracker'!D2:D100, B2, 'Daily Tracker'!J2:J100) | N2: =SUMIF('Daily Tracker'!D2:D100, B2, 'Daily Tracker'!P2:P100)
A3: CUST-102 | B3: Hotel Royal Milk Account | C3: Cow Milk | D3: Monthly Customer | E3: 9845012345 | F3: Main Street Market #45 | G3: 10 | H3: 10 | I3: 5 | J3: 20 | K3: 15 | L3: Active | M3: =SUMIF('Daily Tracker'!D2:D100, B3, 'Daily Tracker'!J2:J100) | N3: =SUMIF('Daily Tracker'!D2:D100, B3, 'Daily Tracker'!P2:P100)
A4: CUST-103 | B4: Sita Lakshmi | C4: Goat Milk | D4: Daily Customer | E4: 9988776655 | F4: Route 2 - Lakeview Homes | G4: 2 | H4: 1 | I4: 0 | J4: 1 | K4: 0 | L4: Active | M4: =SUMIF('Daily Tracker'!D2:D100, B4, 'Daily Tracker'!J2:J100) | N4: =SUMIF('Daily Tracker'!D2:D100, B4, 'Daily Tracker'!P2:P100)
A5: CUST-104 | B5: City Sweets & Bakery | C5: Cow Milk | D5: Monthly Customer | E5: 9776655443 | F5: Bypass Road #12 | G5: 0 | H5: 0 | I5: 20 | J5: 30 | K5: 25 | L5: Active | M5: =SUMIF('Daily Tracker'!D2:D100, B5, 'Daily Tracker'!J2:J100) | N5: =SUMIF('Daily Tracker'!D2:D100, B5, 'Daily Tracker'!P2:P100)
A6: CUST-105 | B6: Spot Walk-in Buyers | C6: Goat Milk | D6: Time-Being | E6: N/A | F6: Farm Gate Direct | G6: 0 | H6: 0 | I6: 0 | J6: 0 | K6: 0 | L6: Active | M6: =SUMIF('Daily Tracker'!D2:D100, B6, 'Daily Tracker'!J2:J100) | N6: =SUMIF('Daily Tracker'!D2:D100, B6, 'Daily Tracker'!P2:P100)

Sheet Daily Tracker
A1: Date | B1: Milk Category | C1: Customer Type | D1: Registered Customer | E1: 175ml (Qty) | F1: 475ml (Qty) | G1: 500ml (Qty) | H1: 750ml (Qty) | I1: 1000ml (Qty) | J1: Total Litres | K1: Rev 175ml (Rs.) | L1: Rev 475ml (Rs.) | M1: Rev 500ml (Rs.) | N1: Rev 750ml (Rs.) | O1: Rev 1000ml (Rs.) | P1: Total Revenue (Rs.) | Q1: Silage Cost (Rs.) | R1: Grass Cutter Wage (Rs.) | S1: Feed / Punnaku (Rs.) | T1: Other Expense (Rs.) | U1: Total Expenses (Rs.) | V1: Net Profit / Loss (Rs.) | W1: Remarks
A2: 2026-09-07 | B2: Cow Milk | C2: Daily Customer | D2: Route 1 & Spot Sales | E2: 10 | F2: 20 | G2: 15 | H2: 44 | I2: 34 | J2: =(E2*0.175)+(F2*0.475)+(G2*0.5)+(H2*0.75)+(I2*1) | K2: =E2*IF(B2="Goat Milk",'Rates & Settings'!$C$3,'Rates & Settings'!$B$3) | L2: =F2*IF(B2="Goat Milk",'Rates & Settings'!$C$4,'Rates & Settings'!$B$4) | M2: =G2*IF(B2="Goat Milk",'Rates & Settings'!$C$5,'Rates & Settings'!$B$5) | N2: =H2*IF(B2="Goat Milk",'Rates & Settings'!$C$6,'Rates & Settings'!$B$6) | O2: =I2*IF(B2="Goat Milk",'Rates & Settings'!$C$7,'Rates & Settings'!$B$7) | P2: =SUM(K2:O2) | Q2: 0 | R2: 600 | S2: 460 | T2: 0 | U2: =SUM(Q2:T2) | V2: =P2-U2 | W2: Today total farm record
A3: 2026-09-06 | B3: Goat Milk | C3: Daily Customer | D3: Sita Lakshmi & Goat Milk Clients | E3: 12 | F3: 10 | G3: 8 | H3: 15 | I3: 5 | J3: =(E3*0.175)+(F3*0.475)+(G3*0.5)+(H3*0.75)+(I3*1) | K3: =E3*IF(B3="Goat Milk",'Rates & Settings'!$C$3,'Rates & Settings'!$B$3) | L3: =F3*IF(B3="Goat Milk",'Rates & Settings'!$C$4,'Rates & Settings'!$B$4) | M3: =G3*IF(B3="Goat Milk",'Rates & Settings'!$C$5,'Rates & Settings'!$B$5) | N3: =H3*IF(B3="Goat Milk",'Rates & Settings'!$C$6,'Rates & Settings'!$B$6) | O3: =I3*IF(B3="Goat Milk",'Rates & Settings'!$C$7,'Rates & Settings'!$B$7) | P3: =SUM(K3:O3) | Q3: 0 | R3: 600 | S3: 450 | T3: 0 | U3: =SUM(Q3:T3) | V3: =P3-U3 | W3: Weekend sales spurt
A4: 2026-09-05 | B4: Cow Milk | C4: Time-Being | D4: Event & Walk-ins | E4: 5 | F4: 32 | G4: 10 | H4: 42 | I4: 30 | J4: =(E4*0.175)+(F4*0.475)+(G4*0.5)+(H4*0.75)+(I4*1) | K4: =E4*IF(B4="Goat Milk",'Rates & Settings'!$C$3,'Rates & Settings'!$B$3) | L4: =F4*IF(B4="Goat Milk",'Rates & Settings'!$C$4,'Rates & Settings'!$B$4) | M4: =G4*IF(B4="Goat Milk",'Rates & Settings'!$C$5,'Rates & Settings'!$B$5) | N4: =H4*IF(B4="Goat Milk",'Rates & Settings'!$C$6,'Rates & Settings'!$B$6) | O4: =I4*IF(B4="Goat Milk",'Rates & Settings'!$C$7,'Rates & Settings'!$B$7) | P4: =SUM(K4:O4) | Q4: 0 | R4: 650 | S4: 480 | T4: 120 | U4: =SUM(Q4:T4) | V4: =P4-U4 | W4: Cutter overtime wage
A5: 2026-09-04 | B5: Cow Milk | C5: Daily Customer | D5: Route 1 & City Sweets | E5: 8 | F5: 28 | G5: 12 | H5: 38 | I5: 28 | J5: =(E5*0.175)+(F5*0.475)+(G5*0.5)+(H5*0.75)+(I5*1) | K5: =E5*IF(B5="Goat Milk",'Rates & Settings'!$C$3,'Rates & Settings'!$B$3) | L5: =F5*IF(B5="Goat Milk",'Rates & Settings'!$C$4,'Rates & Settings'!$B$4) | M5: =G5*IF(B5="Goat Milk",'Rates & Settings'!$C$5,'Rates & Settings'!$B$5) | N5: =H5*IF(B5="Goat Milk",'Rates & Settings'!$C$6,'Rates & Settings'!$B$6) | O5: =I5*IF(B5="Goat Milk",'Rates & Settings'!$C$7,'Rates & Settings'!$B$7) | P5: =SUM(K5:O5) | Q5: 1200 | R5: 600 | S5: 450 | T5: 0 | U5: =SUM(Q5:T5) | V5: =P5-U5 | W5: New silage batch bought
A6: 2026-09-03 | B6: Goat Milk | C6: Monthly Customer | D6: City Sweets & Bakery | E6: 15 | F6: 20 | G6: 10 | H6: 25 | I6: 10 | J6: =(E6*0.175)+(F6*0.475)+(G6*0.5)+(H6*0.75)+(I6*1) | K6: =E6*IF(B6="Goat Milk",'Rates & Settings'!$C$3,'Rates & Settings'!$B$3) | L6: =F6*IF(B6="Goat Milk",'Rates & Settings'!$C$4,'Rates & Settings'!$B$4) | M6: =G6*IF(B6="Goat Milk",'Rates & Settings'!$C$5,'Rates & Settings'!$B$5) | N6: =H6*IF(B6="Goat Milk",'Rates & Settings'!$C$6,'Rates & Settings'!$B$6) | O6: =I6*IF(B6="Goat Milk",'Rates & Settings'!$C$7,'Rates & Settings'!$B$7) | P6: =SUM(K6:O6) | Q6: 0 | R6: 600 | S6: 500 | T6: 50 | U6: =SUM(Q6:T6) | V6: =P6-U6 | W6: High 1L demand
A7: TOTAL | D7: All Categories | E7: =SUM(E2:E6) | F7: =SUM(F2:F6) | G7: =SUM(G2:G6) | H7: =SUM(H2:H6) | I7: =SUM(I2:I6) | J7: =SUM(J2:J6) | K7: =SUM(K2:K6) | L7: =SUM(L2:L6) | ... V7: =SUM(V2:V6) | W7: Grand Total

Sheet Milk Category Summary
A1: Milk Category Performance Summary
A2: Milk Category | B2: Total Litres Sold | C2: Total Revenue Generated (Rs.) | D2: Revenue Share %
A3: Cow Milk | B3: =SUMIF('Daily Tracker'!B2:B6, "Cow Milk", 'Daily Tracker'!J2:J6) | C3: =SUMIF('Daily Tracker'!B2:B6, "Cow Milk", 'Daily Tracker'!P2:P6) | D3: =IF(C3>0, C3/SUM($C$3:$C$4), 0)
A4: Goat Milk | B4: =SUMIF('Daily Tracker'!B2:B6, "Goat Milk", 'Daily Tracker'!J2:J6) | C4: =SUMIF('Daily Tracker'!B2:B6, "Goat Milk", 'Daily Tracker'!P2:P6) | D4: =IF(C4>0, C4/SUM($C$3:$C$4), 0)

Sheet Rates & Settings
A1: Bottle Size / Item | B1: Cow Milk Rate (Rs.) | C1: Goat Milk Rate (Rs.) | D1: Unit / Measure | E1: Notes & Instructions
A2: 175ml Bottle Selling Price | B2: 15 | C2: 25 | D2: Per Bottle (0.175 L) | E2: Editable: Unit price for 175ml bottle
A3: 475ml Bottle Selling Price | B3: 35 | C3: 60 | D3: Per Bottle (0.475 L) | E3: Editable: Unit price for 475ml bottle
A4: 500ml Bottle Selling Price | B4: 38 | C4: 65 | D4: Per Bottle (0.500 L) | E4: Editable: Unit price for 500ml bottle
A5: 750ml Bottle Selling Price | B5: 50 | C5: 90 | D5: Per Bottle (0.750 L) | E5: Editable: Unit price for 750ml bottle
A6: 1000ml (1L) Bottle Selling Price | B6: 65 | C6: 120 | D6: Per Bottle (1.000 L) | E6: Editable: Unit price for 1000ml (1L) bottle

Sheet Customer Master
A1: Customer ID | B1: Customer Name | C1: Payment Type | D1: Milk Type | E1: Phone Number | F1: Delivery Address / Notes | G1: Status
A2: CUST-101 | B2: Helabojun | C2: Daily Customer | D2: Cow Milk Only | E2: N/A | F2: Route Sales / Spot | G2: Active
A3: CUST-102 | B3: Goat Milk Sales | C3: Daily Customer | D3: Goat Milk Only | E3: N/A | F3: Goat Milk Route | G3: Active
A4: CUST-103 | B4: Ayurveda | C4: Daily Customer | D4: Cow Milk Only | E4: N/A | F4: Ayurveda Center | G4: Active
A5: CUST-104 | B5: Gamini | C5: Daily Customer | D5: Cow Milk Only | E5: N/A | F5: Route Sales | G5: Active
A6: CUST-105 | B6: Lakeside | C6: Weekly Customer | D6: Cow Milk Only | E6: N/A | F6: Lakeside Area | G6: Active
A7: CUST-106 | B7: Mahaiyyawa | C7: Daily Customer | D7: Cow Milk Only | E7: N/A | F7: Mahaiyyawa Route | G7: Active
A8: CUST-107 | B8: Arupola Hotel | C8: Daily Customer | D8: Cow Milk Only | E8: N/A | F8: Arupola Route | G8: Active
A9: CUST-108 | B9: Karthik | C9: Daily Customer | D9: Cow Milk Only | E9: N/A | F9: Town Route | G9: Active
A10: CUST-109 | B10: Logeshwaran | C10: Monthly Customer | D10: Cow Milk Only | E10: N/A | F10: Monthly Account | G10: Active
A11: CUST-110 | B11: Praveen | C11: Monthly Customer | D11: Cow Milk Only | E11: N/A | F11: Monthly Account | G11: Active
A12: CUST-111 | B12: Lekraj | C12: Monthly Customer | D12: Cow Milk Only | E12: N/A | F12: Monthly Account | G12: Active
... A37: CUST-136 | B37: Ahiran | C37: Daily Customer | D37: Cow Milk Only | E37: N/A | F37: Route Sales | G37: Active
